deepfacey/DeepFace.py
deepfacey/__init__.py
deepfacey/api/__init__.py
deepfacey/api/src/__init__.py
deepfacey/api/src/api.py
deepfacey/api/src/app.py
deepfacey/api/src/modules/__init__.py
deepfacey/api/src/modules/core/__init__.py
deepfacey/api/src/modules/core/routes.py
deepfacey/api/src/modules/core/service.py
deepfacey/basemodels/ArcFace.py
deepfacey/basemodels/DeepID.py
deepfacey/basemodels/Dlib.py
deepfacey/basemodels/Facenet.py
deepfacey/basemodels/FbDeepFace.py
deepfacey/basemodels/OpenFace.py
deepfacey/basemodels/SFace.py
deepfacey/basemodels/VGGFace.py
deepfacey/basemodels/__init__.py
deepfacey/commons/__init__.py
deepfacey/commons/constant.py
deepfacey/commons/folder_utils.py
deepfacey/commons/logger.py
deepfacey/commons/package_utils.py
deepfacey/detectors/DetectorWrapper.py
deepfacey/detectors/Dlib.py
deepfacey/detectors/FastMtCnn.py
deepfacey/detectors/MediaPipe.py
deepfacey/detectors/MtCnn.py
deepfacey/detectors/OpenCv.py
deepfacey/detectors/RetinaFace.py
deepfacey/detectors/Ssd.py
deepfacey/detectors/Yolo.py
deepfacey/detectors/YuNet.py
deepfacey/detectors/__init__.py
deepfacey/extendedmodels/Age.py
deepfacey/extendedmodels/Emotion.py
deepfacey/extendedmodels/Gender.py
deepfacey/extendedmodels/Race.py
deepfacey/extendedmodels/__init__.py
deepfacey/models/Demography.py
deepfacey/models/Detector.py
deepfacey/models/FacialRecognition.py
deepfacey/models/__init__.py
deepfacey/modules/__init__.py
deepfacey/modules/demography.py
deepfacey/modules/detection.py
deepfacey/modules/modeling.py
deepfacey/modules/preprocessing.py
deepfacey/modules/realtime.py
deepfacey/modules/recognition.py
deepfacey/modules/representation.py
deepfacey/modules/verification.py
deepfacey-0.0.87.data/data/README.md
deepfacey-0.0.87.data/data/package_info.json
deepfacey-0.0.87.data/data/requirements.txt
deepfacey-0.0.87.dist-info/LICENSE
deepfacey-0.0.87.dist-info/METADATA
deepfacey-0.0.87.dist-info/WHEEL
deepfacey-0.0.87.dist-info/entry_points.txt
deepfacey-0.0.87.dist-info/top_level.txt
deepfacey-0.0.87.dist-info/RECORD
