Metadata-Version: 2.1
Name: deepfacey
Version: 0.0.87
Summary: A Lightweight Face Recognition and Facial Attribute Analysis Framework (Age, Gender, Emotion, Race) for Python
Home-page: https://github.com/serengil/deepface
Author: Sefik Ilkin Serengil
Author-email: serengil@gmail.com
Classifier: Programming Language :: Python :: 3
Classifier: License :: OSI Approved :: MIT License
Classifier: Operating System :: OS Independent
Requires-Python: >=3.5.5
License-File: LICENSE
Requires-Dist: numpy ==1.26.4
Requires-Dist: pandas ==2.2.1
Requires-Dist: gdown ==5.1.0
Requires-Dist: tqdm ==4.66.2
Requires-Dist: pillow ==10.2.0
Requires-Dist: opencv-python ==4.9.0.80
Requires-Dist: tensorflow ==2.15.1
Requires-Dist: keras ==2.15.0
Requires-Dist: Flask ==3.0.2
Requires-Dist: mtcnn ==0.1.0
Requires-Dist: retina-face ==0.0.14
Requires-Dist: fire ==0.6.0
Requires-Dist: gunicorn ==21.2.0
